{
  "dataset_revision": "14efe6ac2635395e768682e0b91ce794b50c7ff3",
  "evaluation_time": 13.074840307235718,
  "kg_co2_emissions": null,
  "mteb_version": "1.12.49",
  "scores": {
    "train": [
      {
        "accuracy": 0.8289556962025315,
        "f1": 0.8000699166155995,
        "f1_weighted": 0.8316948307621714,
        "hf_subset": "default",
        "languages": [
          "eng-Latn"
        ],
        "main_score": 0.8289556962025315,
        "scores_per_experiment": [
          {
            "accuracy": 0.8512658227848101,
            "f1": 0.8247509989634376,
            "f1_weighted": 0.8518065573141606
          },
          {
            "accuracy": 0.8251582278481012,
            "f1": 0.7853138815207781,
            "f1_weighted": 0.8282293310501517
          },
          {
            "accuracy": 0.8536392405063291,
            "f1": 0.8265811079197353,
            "f1_weighted": 0.8547960819450369
          },
          {
            "accuracy": 0.7753164556962026,
            "f1": 0.7748254610807047,
            "f1_weighted": 0.782864487760407
          },
          {
            "accuracy": 0.8607594936708861,
            "f1": 0.8261761623913778,
            "f1_weighted": 0.8605817114089831
          },
          {
            "accuracy": 0.882120253164557,
            "f1": 0.8634597415138369,
            "f1_weighted": 0.8802445704936666
          },
          {
            "accuracy": 0.8299050632911392,
            "f1": 0.7986850883066805,
            "f1_weighted": 0.833104821664212
          },
          {
            "accuracy": 0.7729430379746836,
            "f1": 0.7449661303588959,
            "f1_weighted": 0.7819275165555204
          },
          {
            "accuracy": 0.8275316455696202,
            "f1": 0.7936400740177673,
            "f1_weighted": 0.8304200550088975
          },
          {
            "accuracy": 0.8109177215189873,
            "f1": 0.7623005200827818,
            "f1_weighted": 0.8129731744206797
          }
        ]
      }
    ]
  },
  "task_name": "FinancialPhraseBankClassification"
}